seeed_xiao_nrf52840.py
circuitpython_seeed_xiao_nrf52840-1.0.1.dist-info/LICENSE
circuitpython_seeed_xiao_nrf52840-1.0.1.dist-info/METADATA
circuitpython_seeed_xiao_nrf52840-1.0.1.dist-info/WHEEL
circuitpython_seeed_xiao_nrf52840-1.0.1.dist-info/top_level.txt
circuitpython_seeed_xiao_nrf52840-1.0.1.dist-info/RECORD
