Metadata-Version: 2.1
Name: circuitpython-seeed-xiao-nrf52840
Version: 1.0.1
Summary: Provides access to onboard sensors and battet
Author-email: Adafruit Industries <circuitpython@adafruit.com>
License: MIT
Project-URL: Homepage, https://github.com/furbrain/CircuitPython_seeed_xiao_nRF52840
Keywords: adafruit,blinka,circuitpython,micropython,seeed_xiao_nrf52840,seeed,xiao,nrf52840,accelerometer,microphone,battery
Classifier: Intended Audience :: Developers
Classifier: Topic :: Software Development :: Libraries
Classifier: Topic :: Software Development :: Embedded Systems
Classifier: Topic :: System :: Hardware
Classifier: License :: OSI Approved :: MIT License
Classifier: Programming Language :: Python :: 3
License-File: LICENSE
Requires-Dist: Adafruit-Blinka
Requires-Dist: adafruit-circuitpython-lsm6ds
Provides-Extra: optional
